odoo/addons/connector_jira_tempo/README.rst
odoo/addons/connector_jira_tempo/__init__.py
odoo/addons/connector_jira_tempo/__manifest__.py
odoo/addons/connector_jira_tempo/data/cron.xml
odoo/addons/connector_jira_tempo/i18n/connector_jira_tempo.pot
odoo/addons/connector_jira_tempo/models/__init__.py
odoo/addons/connector_jira_tempo/models/account_analytic_line/__init__.py
odoo/addons/connector_jira_tempo/models/account_analytic_line/common.py
odoo/addons/connector_jira_tempo/models/account_analytic_line/importer.py
odoo/addons/connector_jira_tempo/models/jira_backend/__init__.py
odoo/addons/connector_jira_tempo/models/jira_backend/common.py
odoo/addons/connector_jira_tempo/static/description/icon.png
odoo/addons/connector_jira_tempo/tests/__init__.py
odoo/addons/connector_jira_tempo/tests/common.py
odoo/addons/connector_jira_tempo/tests/test_import_tempo.py
odoo/addons/connector_jira_tempo/tests/fixtures/cassettes/test_import_worklog_status.yaml
odoo/addons/connector_jira_tempo/tests/fixtures/cassettes/test_import_worklog_status_update.yaml
odoo/addons/connector_jira_tempo/tests/fixtures/cassettes/test_import_worklog_status_update2.yaml
odoo/addons/connector_jira_tempo/views/jira_backend_view.xml
odoo/addons/connector_jira_tempo/views/timesheet_account_analytic_line.xml
odoo11_addon_connector_jira_tempo-11.0.1.0.2.dist-info/METADATA
odoo11_addon_connector_jira_tempo-11.0.1.0.2.dist-info/WHEEL
odoo11_addon_connector_jira_tempo-11.0.1.0.2.dist-info/top_level.txt
odoo11_addon_connector_jira_tempo-11.0.1.0.2.dist-info/RECORD
